time_it/__init__.py
time_it/time_def.py
time_it-3.dist-info/METADATA
time_it-3.dist-info/WHEEL
time_it-3.dist-info/licenses/LICENSE.txt
time_it-3.dist-info/RECORD
