Metadata-Version: 2.1
Name: time_it
Version: 3
Summary: A package for timing python code
Project-URL: Homepage, https://github.com/CodeBlanco/python-module-time_it
Author-email: Dan <blancotree1@gmail.com>
License: MIT License
License-File: LICENSE.txt
Classifier: License :: OSI Approved :: MIT License
Classifier: Operating System :: OS Independent
Classifier: Programming Language :: Python :: 3
Requires-Python: >=3.7
